[{"id":0,"teacherName":"1A"},{"id":1,"teacherName":"1B"},{"id":2,"teacherName":"1C"},{"id":3,"teacherName":"2A"},{"id":4,"teacherName":"2B"},{"id":5,"teacherName":"2C"},{"id":6,"teacherName":"3A"},{"id":7,"teacherName":"3B"},{"id":8,"teacherName":"3C"},{"id":9,"teacherName":"4A"},{"id":10,"teacherName":"4B"},{"id":11,"teacherName":"4C"},{"id":12,"teacherName":"5A"},{"id":13,"teacherName":"5B"},{"id":14,"teacherName":"5C"},{"id":15,"teacherName":"7th"},{"id":16,"teacherName":"8th"},{"id":17,"teacherName":"Albert"},{"id":18,"teacherName":"Bennett"},{"id":19,"teacherName":"Kessel"},{"id":20,"teacherName":"Knight"},{"id":21,"teacherName":"Lang"}]